Metadata-Version: 1.2
Name: torchrender
Version: 0.0.2
Summary: UNKNOWN
Home-page: https://github.com/SimLeek/torchrender
Author: SimLeek
Author-email: josh.miklos@gmail.com
Maintainer: SimLeek
Maintainer-email: josh.miklos@gmail.com
License: MIT
Keywords: pytorch,shaders
Platform: UNKNOWN
Classifier: Development Status :: 4 - Beta
Classifier: Intended Audience :: Developers
Classifier: License :: OSI Approved :: MIT License
Classifier: Natural Language :: English
Classifier: Operating System :: OS Independent
Classifier: Programming Language :: Python :: 3.5
Classifier: Programming Language :: Python :: 3.6
Classifier: Programming Language :: Python :: Implementation :: PyPy
